README.md
setup.py
pulumi_honeycomb/__init__.py
pulumi_honeycomb/_inputs.py
pulumi_honeycomb/_utilities.py
pulumi_honeycomb/board.py
pulumi_honeycomb/burn_alert.py
pulumi_honeycomb/column.py
pulumi_honeycomb/dataset.py
pulumi_honeycomb/derived_column.py
pulumi_honeycomb/email_recipient.py
pulumi_honeycomb/get_datasets.py
pulumi_honeycomb/get_query_result.py
pulumi_honeycomb/get_query_specification.py
pulumi_honeycomb/get_recipient.py
pulumi_honeycomb/get_recipients.py
pulumi_honeycomb/get_trigger_recipient.py
pulumi_honeycomb/marker.py
pulumi_honeycomb/marker_setting.py
pulumi_honeycomb/outputs.py
pulumi_honeycomb/pagerduty_recipient.py
pulumi_honeycomb/provider.py
pulumi_honeycomb/pulumi-plugin.json
pulumi_honeycomb/py.typed
pulumi_honeycomb/query.py
pulumi_honeycomb/query_annotation.py
pulumi_honeycomb/slack_recipient.py
pulumi_honeycomb/slo.py
pulumi_honeycomb/trigger.py
pulumi_honeycomb/webhook_recipient.py
pulumi_honeycomb.egg-info/PKG-INFO
pulumi_honeycomb.egg-info/SOURCES.txt
pulumi_honeycomb.egg-info/dependency_links.txt
pulumi_honeycomb.egg-info/not-zip-safe
pulumi_honeycomb.egg-info/requires.txt
pulumi_honeycomb.egg-info/top_level.txt
pulumi_honeycomb/config/__init__.py
pulumi_honeycomb/config/vars.py