Metadata-Version: 2.1
Name: pulumi-honeycomb
Version: 0.0.15
Summary: A Pulumi package for creating and managing honeycomb.io resources.
Home-page: https://github.com/honeycombio/terraform-provider-honeycombio
License: Apache-2.0
Project-URL: Repository, https://github.com/honeycombio/terraform-provider-honeycombio
Keywords: pulumi honeycomb tracing o11y monitoring otel category/utility
Platform: UNKNOWN
